publish.py
fiaas_publish-0.2.0.dist-info/METADATA
fiaas_publish-0.2.0.dist-info/RECORD
fiaas_publish-0.2.0.dist-info/WHEEL
fiaas_publish-0.2.0.dist-info/entry_points.txt
fiaas_publish-0.2.0.dist-info/top_level.txt
fiaas_publish-0.2.0.dist-info/zip-safe
