Metadata-Version: 2.1
Name: fiaas-publish
Version: 0.2.0
Summary: Publish python package to PyPI and Github
Home-page: https://github.com/fiaas/publish
Author: FiaaS developers
Author-email: fiaas@googlegroups.com
License: Apache License
Keywords: pypi github fiaas
Platform: UNKNOWN
Classifier: Development Status :: 3 - Alpha
Classifier: Intended Audience :: Developers
Classifier: License :: OSI Approved :: Apache Software License
Classifier: Operating System :: OS Independent
Classifier: Programming Language :: Python
Classifier: Programming Language :: Python :: 2
Classifier: Programming Language :: Python :: 2.7
Classifier: Programming Language :: Python :: 3
Classifier: Programming Language :: Python :: 3.4
Classifier: Programming Language :: Python :: 3.5
Classifier: Programming Language :: Python :: 3.6
Classifier: Topic :: Internet
Classifier: Topic :: Software Development :: Build Tools
Classifier: Topic :: System :: Software Distribution
Provides-Extra: dev
Provides-Extra: codacy
Provides-Extra: docs
Requires-Dist: six (==1.12.0)
Requires-Dist: GitPython (==2.1.11)
Requires-Dist: twine (==1.12.1)
Requires-Dist: githubrelease (==1.5.8)
Provides-Extra: codacy
Requires-Dist: codacy-coverage; extra == 'codacy'
Provides-Extra: dev
Requires-Dist: tox (==3.6.1); extra == 'dev'
Requires-Dist: mock (==2.0.0); extra == 'dev'
Requires-Dist: pytest (==4.0.2); extra == 'dev'
Requires-Dist: pytest-cov (==2.6.0); extra == 'dev'
Requires-Dist: pytest-html (==1.19.0); extra == 'dev'
Requires-Dist: pytest-sugar (==0.9.2); extra == 'dev'
Requires-Dist: prospector; extra == 'dev'
Provides-Extra: docs
Requires-Dist: Sphinx (>=1.6.3); extra == 'docs'
